pythonvideoannotator_module_regionsfilter/__init__.py
pythonvideoannotator_module_regionsfilter/module.py
pythonvideoannotator_module_regionsfilter/regions_filter.py
Python_video_annotator_module_regions_filter-0.5.18.dist-info/METADATA
Python_video_annotator_module_regions_filter-0.5.18.dist-info/WHEEL
Python_video_annotator_module_regions_filter-0.5.18.dist-info/top_level.txt
Python_video_annotator_module_regions_filter-0.5.18.dist-info/RECORD
