Metadata-Version: 2.1
Name: Python-video-annotator-module-regions-filter
Version: 0.5.18
Summary: UNKNOWN
Home-page: https://bitbucket.org/fchampalimaud/pythonvideoannotator-module-regionsfilter
Author: ['Ricardo Ribeiro']
Author-email: ricardojvr@gmail.com
License: UNKNOWN
Platform: UNKNOWN
